pysoltransfer/__init__.py
pysoltransfer/core.py
pysoltransfer-1.0.1.dist-info/LICENSE
pysoltransfer-1.0.1.dist-info/METADATA
pysoltransfer-1.0.1.dist-info/WHEEL
pysoltransfer-1.0.1.dist-info/top_level.txt
pysoltransfer-1.0.1.dist-info/RECORD
